django_grappelli_extras-1.1.1.dist-info/METADATA
django_grappelli_extras-1.1.1.dist-info/RECORD
django_grappelli_extras-1.1.1.dist-info/WHEEL
django_grappelli_extras-1.1.1.dist-info/top_level.txt
grappelli_extras/__init__.py
grappelli_extras/admin.py
grappelli_extras/ajax.py
grappelli_extras/ajax_urls.py
grappelli_extras/extras.py
grappelli_extras/extras_urls.py
grappelli_extras/models.py
grappelli_extras/utils.py
grappelli_extras/views.py
grappelli_extras/static/ajax/django-ajax.js
grappelli_extras/static/ajax/grp-token.js
grappelli_extras/static/ajax/token.js
grappelli_extras/templates/admin/base.html
grappelli_extras/templates/admin/navbar.html
grappelli_extras/templates/ajax/form.html
grappelli_extras/templates/grappelli/navbar.html
grappelli_extras/templates/print/document.html
